netsuite_graphql_engine/__init__.py
netsuite_graphql_engine/handlers.py
netsuite_graphql_engine/main.py
netsuite_graphql_engine/models.py
netsuite_graphql_engine/mutations.py
netsuite_graphql_engine/queries.py
netsuite_graphql_engine/schema.py
netsuite_graphql_engine/types.py
netsuite_graphql_engine-0.0.3.dist-info/LICENSE
netsuite_graphql_engine-0.0.3.dist-info/METADATA
netsuite_graphql_engine-0.0.3.dist-info/WHEEL
netsuite_graphql_engine-0.0.3.dist-info/RECORD
