Metadata-Version: 2.1
Name: NetSuite-GraphQL-Engine
Version: 0.0.3
Summary: The NetSuite GraphQL Engine simplifies interaction with the NetSuite SuiteTalk API using GraphQL, enabling seamless data access and integration into Python applications.
Home-page: https://github.com/ideabosque/netsuite_graphql_engine
License: MIT
Author: Idea Bosque
Author-email: ideabosque@gmail.com
Requires-Python: >=3.6,<4.0
Classifier: Environment :: Web Environment
Classifier: Intended Audience :: Developers
Classifier: License :: OSI Approved :: MIT License
Classifier: Operating System :: OS Independent
Classifier: Programming Language :: Python
Classifier: Programming Language :: Python :: 3
Classifier: Programming Language :: Python :: 3.6
Classifier: Programming Language :: Python :: 3.7
Classifier: Programming Language :: Python :: 3.8
Classifier: Programming Language :: Python :: 3.9
Classifier: Programming Language :: Python :: 3.10
Classifier: Programming Language :: Python :: 3.11
Classifier: Topic :: Internet :: WWW/HTTP :: Dynamic Content
Classifier: Topic :: Software Development :: Libraries :: Python Modules
Requires-Dist: SuiteTalk-Connector (>=0.0.3,<0.0.4)
Requires-Dist: boto3
Requires-Dist: deepdiff
Requires-Dist: graphene
Requires-Dist: pynamodb
Requires-Dist: silvaengine_dynamodb_base (>=0.0.1,<0.0.2)
Requires-Dist: silvaengine_utility (>=0.0.2,<0.0.3)
Project-URL: Repository, https://github.com/ideabosque/netsuite_graphql_engine
